holteandtalley/__init__.py
holteandtalley/densityProfile.py
holteandtalley/handt.py
holteandtalley/profile.py
holteandtalley/salinityProfile.py
holteandtalley/tempProfile.py
holteandtalley-0.0.2.dist-info/LICENSE
holteandtalley-0.0.2.dist-info/METADATA
holteandtalley-0.0.2.dist-info/WHEEL
holteandtalley-0.0.2.dist-info/top_level.txt
holteandtalley-0.0.2.dist-info/RECORD
