Metadata-Version: 2.1
Name: holteandtalley
Version: 0.0.2
Summary: A python adaptation of the Holte and Talley mixed layer depth algorithm
Home-page: https://github.com/garrettdreyfus/python-holteandtalley
Author: Garrett Finucane
Author-email: garrettdreyfus@gmail.com
License: MIT
Platform: UNKNOWN
Classifier: Programming Language :: Python :: 3
Classifier: License :: OSI Approved :: MIT License
Classifier: Operating System :: OS Independent
Requires-Dist: numpy
